petsard/__init__.py
petsard/adapter.py
petsard/config.py
petsard/config_base.py
petsard/constrainer/__init__.py
petsard/constrainer/constrainer.py
petsard/constrainer/constrainer_base.py
petsard/constrainer/field_combination_constrainer.py
petsard/constrainer/field_constrainer.py
petsard/constrainer/field_proportions_constrainer.py
petsard/constrainer/nan_group_constrainer.py
petsard/evaluator/__init__.py
petsard/evaluator/anonymeter.py
petsard/evaluator/customer_evaluator.py
petsard/evaluator/data_describer_base.py
petsard/evaluator/describer.py
petsard/evaluator/describer_compare.py
petsard/evaluator/describer_describe.py
petsard/evaluator/evaluator.py
petsard/evaluator/evaluator_base.py
petsard/evaluator/mlutility.py
petsard/evaluator/mpuccs.py
petsard/evaluator/sdmetrics.py
petsard/evaluator/stats_base.py
petsard/exceptions.py
petsard/executor.py
petsard/loader/__init__.py
petsard/loader/benchmark_datasets.yaml
petsard/loader/benchmarker.py
petsard/loader/loader.py
petsard/loader/loader_base.py
petsard/loader/loader_pandas.py
petsard/loader/splitter.py
petsard/metadater/__init__.py
petsard/metadater/data.py
petsard/metadater/metadata.py
petsard/metadater/metadater.py
petsard/metadater/schema_inferencer.py
petsard/metadater/stats.py
petsard/processor/__init__.py
petsard/processor/base.py
petsard/processor/discretizing.py
petsard/processor/encoder.py
petsard/processor/mediator.py
petsard/processor/missing.py
petsard/processor/outlier.py
petsard/processor/registry.py
petsard/processor/scaler.py
petsard/processor/schema_transform.py
petsard/reporter/__init__.py
petsard/reporter/reporter.py
petsard/reporter/reporter_base.py
petsard/reporter/reporter_save_data.py
petsard/reporter/reporter_save_report.py
petsard/reporter/reporter_save_schema.py
petsard/reporter/reporter_save_timing.py
petsard/reporter/reporter_save_validation.py
petsard/status.py
petsard/synthesizer/__init__.py
petsard/synthesizer/custom_synthesizer.py
petsard/synthesizer/petsard_gaussian_copula.py
petsard-1.9.0.dist-info/WHEEL
petsard-1.9.0.dist-info/METADATA
petsard-1.9.0.dist-info/RECORD
