Metadata-Version: 2.3
Name: petsard
Version: 1.9.0
Summary: Facilitates data generation algorithm and their evaluation processes
Keywords: petsard,data preprocessing,data generation,data evaluation,synthetic data,privacy,privacy enhancing technologies,PETS,anonymization,differential privacy,data science,machine learning
Author: matheme-justyn
Author-email: matheme-justyn <matheme.justyn@gmail.com>
Classifier: Development Status :: 5 - Production/Stable
Classifier: Natural Language :: English
Classifier: Natural Language :: Chinese (Traditional)
Classifier: Programming Language :: Python :: 3.10
Classifier: Programming Language :: Python :: 3.11
Classifier: Intended Audience :: Developers
Classifier: Intended Audience :: Financial and Insurance Industry
Classifier: Intended Audience :: Legal Industry
Requires-Dist: pandas>=2.3.2,<3
Requires-Dist: pyyaml>=6.0.2,<7
Requires-Dist: numpy>=1.26.4,<2
Requires-Dist: python-dateutil>=2.9.0.post0,<3
Requires-Dist: pytz>=2025.2
Requires-Dist: tzdata>=2025.2
Requires-Dist: requests>=2.32.5,<3
Requires-Dist: anonymeter>=1.0.0,<2
Requires-Dist: sdmetrics>=0.23.0,<1
Requires-Dist: xgboost>=3.0.5
Requires-Dist: imblearn>=0.0
Requires-Dist: scikit-learn>=1.7.1,<2
Requires-Dist: joblib>=1.5.2,<2
Requires-Dist: numba>=0.61.2,<1
Requires-Dist: plotly>=6.3.0,<7
Requires-Dist: scipy>=1.15.3,<2 ; python_full_version < '3.11'
Requires-Dist: scipy>=1.16.0,<2 ; python_full_version >= '3.11'
Requires-Dist: sdv>=1.26.0,<2
Requires-Dist: torch>=2.8.0,<3
Requires-Dist: boto3>=1.40.25,<2
Requires-Dist: botocore>=1.40.25,<2
Requires-Dist: faker>=37.6.0,<38
Requires-Dist: filelock>=3.19.1,<4
Requires-Dist: narwhals>=1.45.0,<3
Requires-Dist: platformdirs>=4.4.0,<5
Requires-Dist: s3transfer>=0.13.1,<1
Requires-Dist: threadpoolctl>=3.6.0,<4
Requires-Dist: typing-extensions>=4.15.0,<5
Requires-Dist: urllib3>=2.5.0,<3
Requires-Dist: fsspec>=2025.9.0
Requires-Dist: jinja2>=3.1.6,<4
Requires-Dist: networkx>=3.4.2,<3.5 ; python_full_version < '3.11'
Requires-Dist: networkx>=3.5,<4 ; python_full_version >= '3.11'
Requires-Dist: nvidia-cublas-cu12>=12.6.4.1,<13 ; platform_machine == 'x86_64' and sys_platform == 'linux'
Requires-Dist: nvidia-cuda-cupti-cu12>=12.6.80,<13 ; platform_machine == 'x86_64' and sys_platform == 'linux'
Requires-Dist: nvidia-cuda-nvrtc-cu12>=12.6.77,<13 ; platform_machine == 'x86_64' and sys_platform == 'linux'
Requires-Dist: nvidia-cuda-runtime-cu12>=12.6.77,<13 ; platform_machine == 'x86_64' and sys_platform == 'linux'
Requires-Dist: nvidia-cudnn-cu12>=9.5.1.17,<10 ; platform_machine == 'x86_64' and sys_platform == 'linux'
Requires-Dist: nvidia-cufft-cu12>=11.3.0.4,<12 ; platform_machine == 'x86_64' and sys_platform == 'linux'
Requires-Dist: nvidia-cufile-cu12>=1.11.1.6,<2 ; platform_machine == 'x86_64' and sys_platform == 'linux'
Requires-Dist: nvidia-curand-cu12>=10.3.7.77,<11 ; platform_machine == 'x86_64' and sys_platform == 'linux'
Requires-Dist: nvidia-cusolver-cu12>=11.7.1.2,<12 ; platform_machine == 'x86_64' and sys_platform == 'linux'
Requires-Dist: nvidia-cusparse-cu12>=12.5.4.2,<13 ; platform_machine == 'x86_64' and sys_platform == 'linux'
Requires-Dist: nvidia-cusparselt-cu12>=0.6.3,<1 ; platform_machine == 'x86_64' and sys_platform == 'linux'
Requires-Dist: nvidia-nccl-cu12>=2.26.2,<3 ; platform_machine == 'x86_64' and sys_platform == 'linux'
Requires-Dist: nvidia-nvjitlink-cu12>=12.6.85,<13 ; platform_machine == 'x86_64' and sys_platform == 'linux'
Requires-Dist: nvidia-nvtx-cu12>=12.6.77,<13 ; platform_machine == 'x86_64' and sys_platform == 'linux'
Requires-Dist: sympy>=1.14.0,<2
Requires-Dist: triton>=3.4.0,<4 ; platform_machine == 'x86_64' and sys_platform == 'linux'
Requires-Dist: ipykernel>=6.30.1,<7 ; extra == 'all'
Requires-Dist: ipython>=8.3.0,<9 ; python_full_version < '3.11' and extra == 'all'
Requires-Dist: ipython>=9.4.0,<10 ; python_full_version >= '3.11' and extra == 'all'
Requires-Dist: jupyterlab>=4.4.7,<5 ; extra == 'all'
Requires-Dist: notebook>=7.4.5,<8 ; extra == 'all'
Requires-Dist: pyzmq>=27.0.2,<28 ; extra == 'all'
Requires-Dist: debugpy>=1.8.16,<2 ; extra == 'all'
Requires-Dist: decorator>=5.2.1,<6 ; extra == 'all'
Requires-Dist: ipython-pygments-lexers>=1.1.1,<2 ; python_full_version >= '3.11' and extra == 'all'
Requires-Dist: prompt-toolkit>=3.0.52,<4 ; extra == 'all'
Requires-Dist: psutil>=7.0.0,<8 ; extra == 'all'
Requires-Dist: openpyxl>=3.1.5,<4 ; extra == 'all'
Requires-Dist: ipykernel>=6.30.1,<7 ; extra == 'dev'
Requires-Dist: ipython>=8.3.0,<9 ; python_full_version < '3.11' and extra == 'dev'
Requires-Dist: ipython>=9.4.0,<10 ; python_full_version >= '3.11' and extra == 'dev'
Requires-Dist: jupyterlab>=4.4.7,<5 ; extra == 'dev'
Requires-Dist: notebook>=7.4.5,<8 ; extra == 'dev'
Requires-Dist: pyzmq>=27.0.2,<28 ; extra == 'dev'
Requires-Dist: debugpy>=1.8.16,<2 ; extra == 'dev'
Requires-Dist: decorator>=5.2.1,<6 ; extra == 'dev'
Requires-Dist: ipython-pygments-lexers>=1.1.1,<2 ; python_full_version >= '3.11' and extra == 'dev'
Requires-Dist: prompt-toolkit>=3.0.52,<4 ; extra == 'dev'
Requires-Dist: psutil>=7.0.0,<8 ; extra == 'dev'
Requires-Dist: openpyxl>=3.1.5,<4 ; extra == 'dev'
Requires-Dist: pip-audit>=2.7.3 ; extra == 'dev'
Requires-Dist: pytest>=8.4.2 ; extra == 'dev'
Requires-Dist: pytest-cov>=6.3.0 ; extra == 'dev'
Requires-Dist: python-semantic-release>=10.3.2 ; extra == 'dev'
Requires-Dist: ruff>=0.12.12 ; extra == 'dev'
Requires-Dist: trove-classifiers>=2025.8.26.11 ; extra == 'dev'
Requires-Dist: ipykernel>=6.30.1,<7 ; extra == 'ds'
Requires-Dist: ipython>=8.3.0,<9 ; python_full_version < '3.11' and extra == 'ds'
Requires-Dist: ipython>=9.4.0,<10 ; python_full_version >= '3.11' and extra == 'ds'
Requires-Dist: jupyterlab>=4.4.7,<5 ; extra == 'ds'
Requires-Dist: notebook>=7.4.5,<8 ; extra == 'ds'
Requires-Dist: pyzmq>=27.0.2,<28 ; extra == 'ds'
Requires-Dist: debugpy>=1.8.16,<2 ; extra == 'ds'
Requires-Dist: decorator>=5.2.1,<6 ; extra == 'ds'
Requires-Dist: ipython-pygments-lexers>=1.1.1,<2 ; python_full_version >= '3.11' and extra == 'ds'
Requires-Dist: prompt-toolkit>=3.0.52,<4 ; extra == 'ds'
Requires-Dist: psutil>=7.0.0,<8 ; extra == 'ds'
Requires-Dist: openpyxl>=3.1.5,<4 ; extra == 'excel'
Requires-Dist: ipykernel>=6.30.1,<7 ; extra == 'jupyter'
Requires-Dist: ipython>=8.3.0,<9 ; python_full_version < '3.11' and extra == 'jupyter'
Requires-Dist: ipython>=9.4.0,<10 ; python_full_version >= '3.11' and extra == 'jupyter'
Requires-Dist: jupyterlab>=4.4.7,<5 ; extra == 'jupyter'
Requires-Dist: notebook>=7.4.5,<8 ; extra == 'jupyter'
Requires-Dist: pyzmq>=27.0.2,<28 ; extra == 'jupyter'
Requires-Dist: debugpy>=1.8.16,<2 ; extra == 'jupyter'
Requires-Dist: decorator>=5.2.1,<6 ; extra == 'jupyter'
Requires-Dist: ipython-pygments-lexers>=1.1.1,<2 ; python_full_version >= '3.11' and extra == 'jupyter'
Requires-Dist: prompt-toolkit>=3.0.52,<4 ; extra == 'jupyter'
Requires-Dist: psutil>=7.0.0,<8 ; extra == 'jupyter'
Requires-Python: >=3.10, <3.12
Project-URL: Bug Tracker, https://github.com/nics-tw/petsard/issues
Project-URL: Documentation, https://nics-tw.github.io/petsard/
Project-URL: Repository, https://github.com/nics-tw/petsard
Provides-Extra: all
Provides-Extra: dev
Provides-Extra: ds
Provides-Extra: excel
Provides-Extra: jupyter
